{"schema":{"fields":[{"name":"lng","type":"number"},{"name":"lat","type":"number"},{"name":"Year","type":"string"},{"name":"Country","type":"string"},{"name":"size","type":"integer"},{"name":"color","type":"string"}],"primaryKey":["lng","lat"],"pandas_version":"1.4.0"},"data":[{"lng":-98.3,"lat":61.5,"Year":1967,"Country":"Canada","size":64,"color":"blue"},{"lng":-71.5,"lat":-35.7,"Year":1967,"Country":"Chile","size":49,"color":"green"},{"lng":-41.5,"lat":71.7,"Year":1967,"Country":"Greenland","size":21,"color":"red"},{"lng":-19.0,"lat":64.9,"Year":1967,"Country":"Iceland","size":105,"color":"red"},{"lng":67.3,"lat":48.0,"Year":1967,"Country":"Kazakhstan","size":21,"color":"orange"},{"lng":74.6,"lat":41.2,"Year":1967,"Country":"Kyrgyzstan","size":45,"color":"orange"},{"lng":15.5,"lat":62.4,"Year":1967,"Country":"Sweden","size":5,"color":"red"},{"lng":8.2,"lat":46.8,"Year":1967,"Country":"Switzerland","size":137,"color":"red"},{"lng":-100.3,"lat":39.5,"Year":1967,"Country":"USA","size":212,"color":"blue"}]}